pysurveyx/__init__.py
pysurveyx/datasets.py
pysurveyx/design.py
pysurveyx/domain.py
pysurveyx/estimators.py
pysurveyx/exceptions.py
pysurveyx/glm.py
pysurveyx/glm_helper.py
pysurveyx/loaders.py
pysurveyx/poststrat.py
pysurveyx/quantiles.py
pysurveyx/quantreg.py
pysurveyx/replicate.py
pysurveyx/report.py
pysurveyx/reportgen.py
pysurveyx/variance.py
pysurveyx/viz.py
pysurveyx-0.21.0.dist-info/METADATA
pysurveyx-0.21.0.dist-info/WHEEL
pysurveyx-0.21.0.dist-info/top_level.txt
pysurveyx-0.21.0.dist-info/RECORD
